{
  "id": "depression-ce-nest-pas-une-fatalite",
  "title": "Dépression : ce n'est pas une fatalité",
  "type": "article",
  "excerpt": "La dépression touchera près d'une personne sur cinq en France. Maladie réelle, elle se soigne. TCC, psychanalyse, neurosciences, témoignages et routines concrètes : le dossier complet pour comprendre — et s'en sortir.",
  "content": "<p>La dépression n'est ni un caprice, ni une faiblesse de caractère, ni « un coup de mou qui passera ». C'est une maladie — l'une des plus répandues au monde — et c'est précisément parce que c'est une maladie qu'elle se soigne. Dans ce dossier, Oui Psycho! croise les regards des thérapies cognitivo-comportementales (TCC), de la psychanalyse et des approches les plus récentes, donne la parole à celles et ceux qui en sont sortis, et détaille ce qui fonctionne vraiment — et pourquoi.</p>\n\n<h2>Dépression ou déprime : de quoi parle-t-on exactement ?</h2>\n<p>Tout le monde connaît des passages à vide : une rupture, un deuil, une fatigue accumulée. Ces moments de tristesse sont normaux, proportionnés à ce que nous vivons, et ils s'estompent avec le temps. La dépression — que les psychiatres appellent <em>épisode dépressif caractérisé</em> — est autre chose. Elle s'installe, elle envahit, elle transforme le rapport au monde.</p>\n<p>Pour parler de dépression, les classifications internationales exigent la présence, pendant au moins deux semaines et presque tous les jours, d'une humeur triste ou d'une perte d'intérêt et de plaisir (l'anhédonie), accompagnées d'autres symptômes : fatigue intense, troubles du sommeil et de l'appétit, ralentissement ou agitation, difficultés de concentration, sentiment de dévalorisation ou de culpabilité excessive, et parfois pensées de mort.</p>\n<p>Selon l'Organisation mondiale de la santé, environ 280 millions de personnes vivent avec une dépression dans le monde. En France, près d'une personne sur cinq connaîtra un épisode dépressif au cours de sa vie. Autrement dit : si ce n'est pas vous, c'est quelqu'un que vous aimez. Et pourtant, la honte et l'idée reçue du « secoue-toi » retardent encore massivement l'accès aux soins.</p>\n<h3>Ce que la dépression n'est pas</h3>\n<ul>\n<li><strong>Un manque de volonté.</strong> La perte d'élan est un symptôme de la maladie, pas sa cause.</li>\n<li><strong>Une tristesse ordinaire.</strong> Beaucoup de personnes déprimées décrivent moins une tristesse qu'un vide, une anesthésie émotionnelle.</li>\n<li><strong>Une fatalité.</strong> Les traitements actuels — psychothérapies, médicaments quand ils sont indiqués, changements de mode de vie — permettent une amélioration nette dans la grande majorité des cas.</li>\n</ul>\n\n<h2>Le regard des TCC : quand la pensée s'emballe contre soi</h2>\n<p>Pour les thérapies cognitivo-comportementales, la dépression s'auto-entretient par un cercle vicieux entre pensées, émotions et comportements. Le psychiatre américain Aaron Beck, pionnier de l'approche, a décrit la fameuse <strong>triade cognitive</strong> : une vision négative de soi (« je suis nul »), du monde (« rien n'a de sens ») et de l'avenir (« ça ne changera jamais »).</p>\n<p>Ces pensées ne sont pas des observations neutres : ce sont des <em>distorsions cognitives</em>, des filtres qui déforment systématiquement la réalité. Le cerveau déprimé généralise (« j'ai raté cette réunion, je rate tout »), lit dans les pensées (« il ne m'a pas répondu, il me méprise »), disqualifie le positif (« ce compliment, c'était par politesse »).</p>\n<p>Côté comportement, la dépression pousse au retrait : on annule, on s'isole, on reste au lit. Ce retrait est compréhensible — tout coûte — mais il prive la personne des rares sources de plaisir et d'accomplissement qui lui restent, ce qui aggrave l'humeur, ce qui renforce le retrait. La boucle est bouclée.</p>\n<h3>Comment les TCC cassent le cercle</h3>\n<p>Le thérapeute TCC travaille sur les deux fronts. Sur le front cognitif, il apprend au patient à repérer ses pensées automatiques, à les mettre à distance et à les confronter aux faits — non pas pour « penser positif », mais pour penser <em>juste</em>. Sur le front comportemental, l'<strong>activation comportementale</strong> consiste à réintroduire progressivement, de façon planifiée, des activités porteuses de plaisir ou de sens, sans attendre d'en avoir envie. Car c'est l'un des grands renversements des TCC : dans la dépression, l'action précède la motivation, et non l'inverse.</p>\n\n<h2>Le regard psychanalytique : ce que la dépression raconte</h2>\n<p>La psychanalyse ne regarde pas d'abord les symptômes, mais ce qu'ils expriment. Dans son texte fondateur « Deuil et mélancolie » (1917), Freud compare la dépression au deuil : dans les deux cas, il y a une perte. Mais là où l'endeuillé sait ce qu'il a perdu, le déprimé, lui, a souvent perdu quelque chose sans pouvoir le nommer — un idéal, une image de soi, un amour ancien. Et surtout, observe Freud, le mélancolique retourne contre lui-même les reproches qu'il ne peut adresser à l'objet perdu : l'autoaccusation féroce du déprimé serait une colère qui a fait demi-tour.</p>\n<p>Cette lecture éclaire des aspects que la clinique retrouve constamment : la culpabilité disproportionnée, le sentiment d'indignité, le lien fréquent entre dépression et pertes précoces, séparations, blessures narcissiques. Pour l'approche psychodynamique, le travail thérapeutique consiste à remettre en circulation ce qui s'est figé : nommer la perte, réhabiliter la colère légitime, comprendre ce que l'épisode actuel rejoue d'une histoire plus ancienne.</p>\n<p>TCC et psychanalyse s'opposent moins qu'on ne le croit : la première outille le présent, la seconde donne du sens à l'histoire. Beaucoup de patients bénéficient des deux, successivement ou en parallèle.</p>\n\n<h2>Ce que disent les recherches actuelles</h2>\n<p>Les vingt dernières années ont profondément renouvelé la compréhension de la dépression.</p>\n<h3>Un cerveau qui perd en plasticité — et qui peut la retrouver</h3>\n<p>Les neurosciences décrivent la dépression comme un état où la <strong>neuroplasticité</strong> — la capacité du cerveau à créer et remodeler ses connexions — est mise à mal, notamment dans l'hippocampe et le cortex préfrontal. Bonne nouvelle : les traitements efficaces, qu'ils soient médicamenteux, psychothérapeutiques ou liés à l'exercice physique, semblent précisément restaurer cette plasticité. Le cerveau déprimé n'est pas abîmé pour toujours : il est en attente de conditions favorables.</p>\n<h3>Le rôle de l'inflammation et du mode de vie</h3>\n<p>Chez une partie des patients, la dépression s'accompagne d'une inflammation de bas grade, ce qui explique les liens observés avec le stress chronique, le manque de sommeil, la sédentarité et certaines maladies somatiques. C'est l'un des arguments scientifiques derrière les recommandations sur l'activité physique, le sommeil et l'alimentation : elles n'ont rien de gadgets « bien-être », elles agissent sur la biologie même de la maladie.</p>\n<h3>La troisième vague : pleine conscience et acceptation</h3>\n<p>Les thérapies dites de « troisième vague » (thérapie cognitive basée sur la pleine conscience ou MBCT, thérapie d'acceptation et d'engagement ou ACT) ne cherchent pas tant à modifier le contenu des pensées qu'à changer la relation qu'on entretient avec elles. La MBCT, en particulier, a démontré son efficacité pour prévenir les rechutes chez les personnes ayant connu plusieurs épisodes dépressifs — un enjeu majeur, car la rechute est le talon d'Achille de cette maladie.</p>\n<h3>Et les nouvelles pistes ?</h3>\n<p>Pour les dépressions résistantes, la recherche explore la kétamine et l'eskétamine (à action rapide, sous strict encadrement hospitalier), la stimulation magnétique transcrânienne, et des programmes de psychothérapie numérique. Ces approches ne remplacent pas les traitements de référence, mais elles élargissent l'arsenal pour les situations les plus difficiles.</p>\n\n<h2>« Je pensais que c'était moi, le problème » : ils témoignent</h2>\n<blockquote><p>« Pendant des mois, je me levais épuisée d'une nuit de dix heures. Je souriais au travail et je pleurais dans ma voiture. Le jour où mon médecin a prononcé le mot dépression, j'ai d'abord été vexée. Puis soulagée : si c'était une maladie, alors ce n'était pas ma personnalité. » — Claire, 34 ans</p></blockquote>\n<blockquote><p>« Ce qui m'a sauvé, c'est l'activation comportementale. Ma psy me faisait planifier des choses ridicules : marcher dix minutes, appeler un ami. Je le faisais sans envie, mécaniquement. Et un jour, en marchant, j'ai remarqué que je regardais les arbres. C'était infime, mais c'était le début. » — Mehdi, 41 ans</p></blockquote>\n<blockquote><p>« En analyse, j'ai compris que je m'effondrais chaque fois que je réussissais quelque chose. Comme si je n'y avais pas droit. Remonter le fil de cette interdiction a changé quelque chose de plus profond que mes symptômes : mon rapport à moi-même. » — Sophie, 52 ans</p></blockquote>\n<p><em>Les prénoms ont été modifiés. Ces témoignages sont des récits composites inspirés de parcours cliniques réels.</em></p>\n\n<h2>S'en sortir : ce qui marche, et pourquoi ça marche</h2>\n<h3>1. La psychothérapie : le traitement de fond</h3>\n<p>Les méta-analyses les plus récentes le confirment : les psychothérapies structurées (TCC, activation comportementale, thérapie interpersonnelle, approches psychodynamiques) sont efficaces contre la dépression, avec des effets qui se maintiennent dans le temps. Pourquoi ça marche ? Parce qu'elles ne se contentent pas de soulager : elles modifient les mécanismes qui entretiennent la maladie — boucles de rumination, évitement, conflits relationnels, scénarios intérieurs — et donnent des outils réutilisables en cas de coup dur.</p>\n<h3>2. Les antidépresseurs : utiles quand ils sont indiqués</h3>\n<p>Pour les dépressions d'intensité modérée à sévère, les antidépresseurs ont fait la preuve de leur efficacité, idéalement en association avec une psychothérapie. Ils ne sont ni des « pilules du bonheur » ni des drogues qui rendent dépendant : ils rétablissent progressivement, en plusieurs semaines, un fonctionnement neurobiologique qui permet de redevenir accessible au changement. La décision se prend avec un médecin, jamais seul — et l'arrêt aussi.</p>\n<h3>3. L'activité physique : un antidépresseur naturel documenté</h3>\n<p>L'exercice régulier — même modéré, même la marche — a un effet antidépresseur démontré par de nombreuses études. Les mécanismes sont multiples : stimulation de la neuroplasticité, réduction de l'inflammation, amélioration du sommeil, sentiment d'efficacité retrouvé. Le bon dosage de départ : celui que vous pouvez tenir. Dix minutes valent infiniment mieux que zéro.</p>\n<h3>4. Le sommeil, le lien social, la lumière</h3>\n<p>Régulariser ses horaires de sommeil, s'exposer à la lumière du jour le matin, maintenir un minimum de contacts sociaux même brefs : ces leviers paraissent modestes, mais ils agissent sur les rythmes biologiques et le sentiment d'appartenance, deux piliers fragilisés par la dépression.</p>\n<h3>5. La pleine conscience contre la rechute</h3>\n<p>Après deux épisodes ou plus, un programme de type MBCT réduit significativement le risque de rechute. Le principe : apprendre à repérer très tôt les premiers signes de rumination et à s'en désengager, avant que la spirale ne s'installe.</p>\n\n<h2>Routines et tips : le kit de démarrage, pas à pas</h2>\n<p>Attention, prérequis honnête : ces outils accompagnent un parcours de soin, ils ne le remplacent pas. Si vous vous reconnaissez dans les symptômes décrits plus haut, la première « routine » est de consulter.</p>\n<ol>\n<li><strong>La règle des petits pas.</strong> Choisissez une action minuscule — tellement petite qu'il est presque impossible d'échouer — et faites-la chaque jour. Ouvrir les volets. Boire un verre d'eau au réveil. La dépression se combat à l'échelle du geste, pas de la révolution.</li>\n<li><strong>Planifiez, ne décidez pas sur le moment.</strong> Le matin (ou la veille), inscrivez une ou deux activités dans votre journée : une agréable, une utile. Puis exécutez le plan comme une ordonnance, sans consulter votre envie — elle mentira.</li>\n<li><strong>Le lever à heure fixe.</strong> Plus encore que l'heure du coucher, c'est l'heure du lever qui resynchronise l'horloge interne. Même après une mauvaise nuit, même le week-end (à une heure près).</li>\n<li><strong>Quinze minutes dehors avant midi.</strong> Lumière naturelle + mouvement : deux leviers biologiques pour le prix d'une promenade.</li>\n<li><strong>Le rendez-vous rumination.</strong> Quand les pensées tournent en boucle, notez-les et donnez-leur rendez-vous : quinze minutes, à heure fixe, stylo en main. Hors de ce créneau, ramenez doucement l'attention sur l'activité en cours. C'est un muscle : il se renforce.</li>\n<li><strong>Un contact humain par jour.</strong> Un message, un appel de trois minutes, un bonjour au commerçant. L'isolement est le carburant de la dépression ; le lien, même minimal, est son antidote.</li>\n<li><strong>Le journal des trois lignes.</strong> Chaque soir : une chose faite (même minuscule), une sensation agréable (même fugace), une chose prévue pour demain. Ce n'est pas de la pensée positive : c'est un entraînement de l'attention, qui, déprimée, ne voit plus que le négatif.</li>\n<li><strong>Suspendez les grandes décisions.</strong> Déménagement, rupture, démission : la dépression déforme le jugement. Sauf urgence, les grandes décisions attendront que le brouillard se lève.</li>\n</ol>\n\n<h2>Le carnet de suivi : votre tableau de bord</h2>\n<p>Suivre son humeur par écrit n'est pas un gadget : c'est un outil clinique. Il objective les progrès (que la mémoire déprimée efface), révèle les liens entre activités et moral, et donne à votre thérapeute ou médecin une matière précieuse. Un carnet de suivi efficace tient en cinq colonnes quotidiennes :</p>\n<ul>\n<li><strong>Humeur du jour</strong> : une note de 0 à 10, matin et soir.</li>\n<li><strong>Sommeil</strong> : heure de lever, qualité ressentie.</li>\n<li><strong>Activités réalisées</strong> : cochées, avec un P (plaisir) ou un A (accomplissement).</li>\n<li><strong>Une pensée marquante</strong> : notée telle quelle, sans la juger.</li>\n<li><strong>Un fait positif</strong> : même microscopique.</li>\n</ul>\n<p>Vous pouvez le tenir sur un simple cahier dès ce soir. Une version à imprimer, ainsi que d'autres supports (coloriages apaisants, liens vers des méditations guidées), rejoindront prochainement la rubrique Outils de Oui Psycho! — on y travaille.</p>\n\n<h2>Quand consulter, qui consulter ?</h2>\n<p>Consultez sans attendre si les symptômes durent depuis plus de deux semaines, s'ils retentissent sur votre travail, vos relations ou votre santé, ou si des pensées de mort apparaissent. Le premier interlocuteur peut être votre médecin traitant, qui évaluera la situation et vous orientera. Les psychologues (dont certains sont accessibles via le dispositif Mon soutien psy), les psychiatres (remboursés, habilités à prescrire) et les centres médico-psychologiques (CMP, gratuits) sont les autres portes d'entrée.</p>\n<p><strong>En cas de pensées suicidaires, ne restez pas seul·e : le 3114</strong>, numéro national de prévention du suicide, est gratuit, confidentiel et joignable 24h/24, 7j/7, partout en France. En cas de danger immédiat, appelez le 15.</p>\n\n<h2>Ce qu'il faut retenir</h2>\n<p>La dépression est une maladie fréquente, sérieuse — et qui se soigne. Les TCC démontent ses mécanismes d'entretien, la psychanalyse éclaire son sens dans une histoire, les neurosciences confirment que le cerveau déprimé peut se réparer. Entre psychothérapie, traitements quand ils sont indiqués, mouvement, lumière, lien et petits pas quotidiens, les chemins de sortie sont multiples et documentés. Non, ce n'est pas une fatalité. Oui, on en sort. Et le premier pas — souvent le plus difficile — est aussi le plus simple : en parler.</p>",
  "date": "2026-10-23",
  "date_modified": "2026-07-10",
  "category": "Troubles Psy",
  "image": "https://res.cloudinary.com/druutw29p/image/upload/f_auto,q_auto,w_1200/ouipsycho/articles/etrpv8ospcqjweg6vlbi",
  "imagePosition": "50% 50%",
  "imageZoom": 1,
  "imageGravity": "none",
  "imageLayout": "top",
  "readTime": 16,
  "author": "La rédaction Oui Psycho!",
  "tags": [
    "depression",
    "tcc",
    "psychanalyse",
    "sante-mentale",
    "therapies"
  ],
  "metaDescription": "Dépression : symptômes, regards des TCC et de la psychanalyse, avancées scientifiques, témoignages et solutions concrètes pour s'en sortir. Dossier complet.",
  "keypoints": [
    "La dépression est une maladie fréquente et sérieuse, jamais une faiblesse de caractère.",
    "Les TCC cassent le cercle vicieux pensées négatives, retrait et perte de plaisir.",
    "La psychanalyse éclaire la perte cachée et la colère retournée contre soi.",
    "Psychothérapie, exercice, sommeil et lien social ont une efficacité scientifiquement démontrée.",
    "Des routines quotidiennes minuscules et un carnet de suivi accélèrent concrètement la sortie."
  ],
  "sources": [
    {
      "authors": "Organisation mondiale de la santé",
      "year": "2023",
      "title": "Troubles dépressifs (dépression) — Principaux repères",
      "journal": "OMS",
      "url": "https://www.who.int/fr/news-room/fact-sheets/detail/depression"
    },
    {
      "authors": "Beck A. T., Rush A. J., Shaw B. F. & Emery G.",
      "year": "1979",
      "title": "Cognitive Therapy of Depression",
      "publisher": "Guilford Press",
      "amazon_asin": "0898629195"
    },
    {
      "authors": "Freud S.",
      "year": "1917",
      "title": "Deuil et mélancolie",
      "publisher": "Presses Universitaires de France (trad. fr.)"
    },
    {
      "authors": "Cuijpers P., Quero S., Noma H. et al.",
      "year": "2021",
      "title": "Psychotherapies for depression: a network meta-analysis covering efficacy, acceptability and long-term outcomes",
      "journal": "World Psychiatry",
      "url": "https://doi.org/10.1002/wps.20860"
    },
    {
      "authors": "Schuch F. B., Vancampfort D., Richards J. et al.",
      "year": "2016",
      "title": "Exercise as a treatment for depression: A meta-analysis adjusting for publication bias",
      "journal": "Journal of Psychiatric Research",
      "url": "https://doi.org/10.1016/j.jpsychires.2016.02.023"
    },
    {
      "authors": "Kuyken W., Warren F. C., Taylor R. S. et al.",
      "year": "2016",
      "title": "Efficacy of Mindfulness-Based Cognitive Therapy in Prevention of Depressive Relapse",
      "journal": "JAMA Psychiatry",
      "url": "https://doi.org/10.1001/jamapsychiatry.2016.0076"
    },
    {
      "authors": "Otte C., Gold S. M., Penninx B. W. et al.",
      "year": "2016",
      "title": "Major depressive disorder",
      "journal": "Nature Reviews Disease Primers",
      "url": "https://doi.org/10.1038/nrdp.2016.65"
    },
    {
      "authors": "Haute Autorité de Santé",
      "year": "2017",
      "title": "Épisode dépressif caractérisé de l'adulte : prise en charge en soins de premier recours",
      "publisher": "HAS"
    },
    {
      "authors": "Inserm",
      "year": "2019",
      "title": "Dépression — Mieux la comprendre pour la guérir durablement (dossier d'information)",
      "publisher": "Inserm"
    }
  ],
  "articles_lies": [],
  "status": "scheduled"
}