{
  "id": "pere-noel-sur-le-divan",
  "title": "Le Père Noël sur le divan : psychologie d'un vieux barbu se déplaçant en traîneau",
  "type": "article",
  "excerpt": "Pourquoi les enfants y croient si fort, et pourquoi des parents raisonnables tiennent tant à entretenir le mythe ? Entre pensée magique, mensonge bienveillant et surveillant surnaturel, le Père Noël en dit long sur nous. Direction le divan.",
  "content": "<p>Un vieil homme jovial, barbu et bedonnant, vêtu de rouge, qui vit au pôle Nord, surveille le comportement de millions d'enfants et parcourt le monde en une nuit sur un traîneau volant pour distribuer des cadeaux : dit comme ça, le <strong>Père Noël</strong> a de quoi intriguer un psychologue. Comment une figure aussi invraisemblable est-elle devenue l'un des personnages les plus aimés de la planète — et surtout, pourquoi des parents raisonnables tiennent-ils tant à y faire croire leurs enfants ? Installons le bonhomme rouge sur le divan (le traîneau restera dehors).</p>\n\n<h2>Pourquoi les enfants y croient dur comme fer</h2>\n<p>Loin d'être une preuve de naïveté, la croyance au Père Noël illustre le fonctionnement normal — et brillant — de l'esprit enfantin. Vers 3 ou 4 ans, l'enfant développe ce que les psychologues appellent la <strong>pensée magique</strong> : la frontière entre réel et imaginaire reste poreuse, et l'extraordinaire y a toute sa place. Surtout, les enfants sont d'excellents petits scientifiques : ils croient ce que les adultes de confiance leur affirment, d'autant plus quand des preuves tangibles s'accumulent — les cadeaux au pied du sapin, les biscuits grignotés, la lettre à laquelle « on » a répondu. Face à un témoignage unanime et à des indices concrets, conclure que le Père Noël existe est, pour un enfant, un raisonnement parfaitement rationnel. Ce ne sont pas eux qui se trompent : c'est nous qui mettons en scène la preuve.</p>\n\n<h2>Le grand mensonge bienveillant des parents</h2>\n<p>Car voilà le vrai mystère psychologique : pourquoi des parents qui interdisent à leurs enfants de mentir orchestrent-ils, chaque année, l'un des mensonges les plus élaborés qui soient ? Les chercheurs parlent de <em>mensonge prosocial</em> : une entorse à la vérité motivée non par l'intérêt personnel, mais par le désir de faire plaisir et de protéger. Entretenir le Père Noël, c'est offrir à son enfant de l'émerveillement, un rituel partagé, un peu de magie dans un monde qui en manque. Les études sur le sujet sont d'ailleurs rassurantes : la découverte de la supercherie ne traumatise quasiment jamais. La plupart des enfants l'accueillent avec un mélange de fierté (« j'ai compris tout seul ») et, tout au plus, une pointe de nostalgie. Rares sont ceux qui en veulent durablement à leurs parents.</p>\n\n<p>Le débat n'est pas totalement tranché pour autant. Quelques psychologues se sont demandé si ce mensonge, si soigneusement entretenu par ceux en qui l'enfant a le plus confiance, ne risquait pas d'entamer un jour cette confiance. La question mérite d'être posée. Mais à ce jour, aucune donnée solide ne met en évidence de dégâts durables : tout se joue surtout dans la manière dont les parents accompagnent la révélation, avec humour et tendresse plutôt que par un démenti brutal. Bien menée, la bascule du « il existe » vers « c'est toi qui prends le relais » ressemble moins à une trahison qu'à un rite de passage.</p>\n\n<h2>Un surveillant qui voit tout : le Père Noël, agent moral</h2>\n<p>« Il sait si tu as été sage ou pas. » Derrière la comptine se cache une fonction sociale limpide : le Père Noël est un formidable outil de régulation du comportement. Un observateur invisible, omniscient, qui récompense les gentils et menace (mollement) les autres d'un morceau de charbon. La psychologie a montré que le simple sentiment d'être observé — même par une présence imaginaire — suffit à nous rendre plus honnêtes et plus coopératifs. Le bonhomme rouge fonctionne comme ces « agents surnaturels » que les anthropologues retrouvent dans quantité de cultures : des figures qui surveillent la morale et poussent, l'air de rien, à mieux se conduire. Un gendarme en costume de peluche, en somme.</p>\n\n<h2>Saint Nicolas, rennes et poème : une longue généalogie</h2>\n<p>Le Père Noël n'est pas tombé du ciel tout équipé. Il descend en droite ligne de <strong>saint Nicolas</strong>, évêque du IV<sup>e</sup> siècle réputé pour sa générosité envers les enfants, et dont la fête se célèbre encore le 6 décembre dans une partie de l'Europe. Emporté par les migrants néerlandais en Amérique sous le nom de <em>Sinterklaas</em>, il y devient « Santa Claus ». En 1823, un poème américain resté célèbre — celui qui s'ouvre sur la nuit précédant Noël — fixe durablement le décor : le traîneau, les huit rennes, la hotte, la descente par la cheminée. Les caricaturistes du XIX<sup>e</sup> siècle, Thomas Nast en tête, lui donnent ensuite sa silhouette joufflue. Le personnage est donc un patchwork de plusieurs siècles et de plusieurs cultures — un mythe cousu main.</p>\n\n<h2>Rouge Coca-Cola : la fabrique d'une icône</h2>\n<p>Contrairement à une légende tenace, Coca-Cola n'a pas inventé le costume rouge du Père Noël — celui-ci existait déjà. Mais la marque a puissamment <strong>standardisé</strong> son image à partir des années 1930, avec ses fameuses illustrations d'un Santa débonnaire, rouge et blanc, jovial à souhait. En une poignée de décennies, une figure aux origines multiples — saint Nicolas, folklores nordiques, esprits de l'hiver — s'est figée en un personnage unique et mondialement reconnaissable. C'est un cas d'école de <em>construction culturelle</em> : une icône façonnée autant par le commerce que par la tradition, et si bien ancrée qu'on la croit éternelle. Le Père Noël moderne est né d'un mélange de mythe, de poésie et de marketing.</p>\n\n<h2>Ce que le vieux barbu nous apprend sur nous</h2>\n<p>Au fond, si le Père Noël nous accompagne depuis si longtemps, c'est qu'il condense plusieurs de nos besoins les plus profonds : croire en une bienveillance qui dépasse le quotidien, ritualiser le don, transmettre de la magie à ceux qu'on aime. Il incarne une générosité gratuite, sans facture ni condition — un idéal réconfortant, surtout à l'âge adulte. Le mettre sur le divan, ce n'est pas dénoncer une imposture, c'est comprendre pourquoi nous tenons tant à cette histoire. Les enfants finiront par savoir. Et beaucoup, devenus grands, remettront le costume rouge avec émotion, pour offrir à leur tour ce petit émerveillement dont ils gardent un souvenir ému. Le Père Noël n'existe peut-être pas — mais le besoin qu'il comble, lui, est bien réel.</p>",
  "date": "2026-12-22",
  "date_modified": "2026-07-06",
  "category": "Nos héros sur le divan",
  "image": "https://res.cloudinary.com/druutw29p/image/upload/f_auto,q_auto,w_1200/ouipsycho/articles/dwnq6uxywpc6ngqny9hy",
  "imagePosition": "50% 50%",
  "imageZoom": 1,
  "imageGravity": "none",
  "imageLayout": "top",
  "readTime": 5,
  "author": "John Balthazar",
  "tags": [
    "père noël",
    "pensée magique",
    "développement de l'enfant",
    "mensonge prosocial",
    "culture pop"
  ],
  "metaDescription": "Pensée magique, mensonge prosocial, agent moral qui voit tout : que dit la psychologie de notre attachement au Père Noël ? Le vieux barbu rouge sur le divan.",
  "keypoints": [
    "Croire au Père Noël n'est pas de la naïveté : c'est le fruit de la « pensée magique » et d'un raisonnement rationnel face aux preuves mises en scène par les adultes.",
    "Les parents pratiquent un « mensonge prosocial » : une entorse à la vérité motivée par l'envie d'émerveiller et de protéger, non par l'intérêt.",
    "Découvrir la supercherie ne traumatise quasiment jamais : la plupart des enfants réagissent avec fierté, tout au plus un brin de nostalgie.",
    "Observateur omniscient qui récompense les sages, le Père Noël agit comme un « agent moral » qui favorise l'honnêteté et la coopération.",
    "Son image rouge et blanche a été standardisée (et non inventée) par Coca-Cola dès les années 1930 : un cas d'école de construction culturelle.",
    "Le personnage est un patchwork de siècles : saint Nicolas, le Sinterklaas néerlandais, un poème de 1823 pour les rennes et le traîneau, les dessins de Thomas Nast."
  ],
  "sources": [
    {
      "authors": "Woolley, J. D. & Ghossainy, M. E.",
      "year": "2013",
      "title": "Revisiting the fantasy-reality distinction: Children as naive skeptics",
      "journal": "Child Development"
    },
    {
      "authors": "Bateson, M., Nettle, D. & Roberts, G.",
      "year": "2006",
      "title": "Cues of being watched enhance cooperation in a real-world setting",
      "journal": "Biology Letters"
    },
    {
      "authors": "Bering, J.",
      "year": "2011",
      "title": "The Belief Instinct",
      "publisher": "W. W. Norton"
    }
  ],
  "articles_lies": [],
  "status": "scheduled"
}